Athenea/__init__.py
Athenea/configs.py
Athenea/diffusion_utils.py
Athenea/encoders.py
Athenea/llm.py
Athenea/transfusion.py
athenea-0.1.8.dist-info/METADATA
athenea-0.1.8.dist-info/WHEEL
athenea-0.1.8.dist-info/licenses/LICENSE
athenea-0.1.8.dist-info/RECORD
